mega_seeds/__init__.py
mega_seeds/cli.py
mega_seeds/models.py
mega_seeds/runner.py
mega_seeds/seeds.py.mako
mega_seeds-0.1.0.dist-info/entry_points.txt
mega_seeds-0.1.0.dist-info/METADATA
mega_seeds-0.1.0.dist-info/WHEEL
mega_seeds-0.1.0.dist-info/RECORD
